rbact/__init__.py
rbact/base_adapter.py
rbact/errors.py
rbact/inspector.py
rbact/peewee/__init__.py
rbact/peewee/models.py
rbact/peewee/peewee_adapter.py
rbact/peewee_async/__init__.py
rbact/peewee_async/peewee_adapter.py
rbact-1.4.1.dist-info/LICENSE
rbact-1.4.1.dist-info/METADATA
rbact-1.4.1.dist-info/WHEEL
rbact-1.4.1.dist-info/top_level.txt
rbact-1.4.1.dist-info/RECORD
