Metadata-Version: 2.1
Name: rbact
Version: 1.4.1
Summary: Simple RBAC library
Home-page: https://github.com/chin-wag/rbact
Author: Svetlana Fedorishcheva
Author-email: svetlanafedorishcheva99@gmail.com
License: MIT
Keywords: rbac,auth,authorization,access control,permission
Platform: UNKNOWN
License-File: LICENSE
Provides-Extra: peewee
Requires-Dist: peewee (>=3.14.1) ; extra == 'peewee'
Provides-Extra: peewee_async
Requires-Dist: peewee (>=3.14.1) ; extra == 'peewee_async'
Requires-Dist: peewee-async (>=0.7.2) ; extra == 'peewee_async'
